eporner/__init__.py
eporner/client.py
eporner/enums.py
eporner/errors.py
eporner/http.py
eporner/models.py
eporner.py-1.0.1.dist-info/LICENSE
eporner.py-1.0.1.dist-info/METADATA
eporner.py-1.0.1.dist-info/WHEEL
eporner.py-1.0.1.dist-info/top_level.txt
eporner.py-1.0.1.dist-info/RECORD
