Metadata-Version: 2.1
Name: eporner.py
Version: 1.0.1
Summary: A simple asynchronous Eporner API wrapper.
Home-page: https://github.com/boobfuck/eporner.py
Author: boobfuck
License: MIT
Project-URL: Documentation, https://epornerpy.readthedocs.io/en/latest
Project-URL: Issue tracker, https://github.com/boobfuck/eporner.py/issues
Platform: UNKNOWN
Requires-Python: >=3.7.0
Requires-Dist: aiohttp
